README.md
setup.py
kdfba/__init__.py
kdfba/dio.py
kdfba/model.py
kdfba/reactions.py
kdfba/solver.py
kdfba/tool.py
kdfba.egg-info/PKG-INFO
kdfba.egg-info/SOURCES.txt
kdfba.egg-info/dependency_links.txt
kdfba.egg-info/requires.txt
kdfba.egg-info/top_level.txt